subst.py
subst-0.4.0.dist-info/DESCRIPTION.rst
subst-0.4.0.dist-info/entry_points.txt
subst-0.4.0.dist-info/METADATA
subst-0.4.0.dist-info/metadata.json
subst-0.4.0.dist-info/RECORD
subst-0.4.0.dist-info/top_level.txt
subst-0.4.0.dist-info/WHEEL
